DLL/__init__.py
DLL/Data/Metrics.py
DLL/Data/Preprocessing.py
DLL/Data/_DataReader.py
DLL/Data/__init__.py
DLL/DeepLearning/Model.py
DLL/DeepLearning/__init__.py
DLL/DeepLearning/Callbacks/_BackUp.py
DLL/DeepLearning/Callbacks/_BaseCallback.py
DLL/DeepLearning/Callbacks/_EarlyStopping.py
DLL/DeepLearning/Callbacks/_ReduceLROnPlateau.py
DLL/DeepLearning/Callbacks/__init__.py
DLL/DeepLearning/Initialisers/_Initialiser.py
DLL/DeepLearning/Initialisers/_Kaiming_He.py
DLL/DeepLearning/Initialisers/_Xavier_Glorot.py
DLL/DeepLearning/Initialisers/__init__.py
DLL/DeepLearning/Layers/_Add.py
DLL/DeepLearning/Layers/_Attention.py
DLL/DeepLearning/Layers/_BaseLayer.py
DLL/DeepLearning/Layers/_Bidirectional.py
DLL/DeepLearning/Layers/_Conv2D.py
DLL/DeepLearning/Layers/_Dense.py
DLL/DeepLearning/Layers/_DenseKAN.py
DLL/DeepLearning/Layers/_Flatten.py
DLL/DeepLearning/Layers/_Identity.py
DLL/DeepLearning/Layers/_Input.py
DLL/DeepLearning/Layers/_LSTM.py
DLL/DeepLearning/Layers/_LayerList.py
DLL/DeepLearning/Layers/_MaxPooling2D.py
DLL/DeepLearning/Layers/_RNN.py
DLL/DeepLearning/Layers/_Reshape.py
DLL/DeepLearning/Layers/__init__.py
DLL/DeepLearning/Layers/Activations/_Activation.py
DLL/DeepLearning/Layers/Activations/_ReLU.py
DLL/DeepLearning/Layers/Activations/_Sigmoid.py
DLL/DeepLearning/Layers/Activations/_SoftMax.py
DLL/DeepLearning/Layers/Activations/_Tanh.py
DLL/DeepLearning/Layers/Activations/__init__.py
DLL/DeepLearning/Layers/Regularisation/_BaseRegularisation.py
DLL/DeepLearning/Layers/Regularisation/_BatchNormalisation.py
DLL/DeepLearning/Layers/Regularisation/_Dropout.py
DLL/DeepLearning/Layers/Regularisation/_GroupNormalisation.py
DLL/DeepLearning/Layers/Regularisation/_InstanceNormalisation.py
DLL/DeepLearning/Layers/Regularisation/_LayerNormalisation.py
DLL/DeepLearning/Layers/Regularisation/__init__.py
DLL/DeepLearning/Losses/_BCE.py
DLL/DeepLearning/Losses/_BaseLoss.py
DLL/DeepLearning/Losses/_CCE.py
DLL/DeepLearning/Losses/_Exponential.py
pydllib-1.0.3.dist-info/licenses/LICENSE
pydllib-1.0.3.dist-info/METADATA
pydllib-1.0.3.dist-info/WHEEL
pydllib-1.0.3.dist-info/top_level.txt
pydllib-1.0.3.dist-info/RECORD
