Metadata-Version: 2.4
Name: PyDLLib
Version: 1.0.3
Summary: A deep and machine learning library. Made for learning purposes and ease of understanding.
Author-email: Aatu Selkee <aatu.selkee@gmail.com>
Project-URL: Homepage, https://naapeli.github.io/deep-learning-library/index.html
Classifier: Programming Language :: Python :: 3
Classifier: License :: OSI Approved :: MIT License
Classifier: Operating System :: OS Independent
Requires-Python: >=3.11.9
License-File: LICENSE
Requires-Dist: cvxopt==1.3.2
Requires-Dist: filelock==3.18.0
Requires-Dist: fsspec==2025.3.0
Requires-Dist: Jinja2==3.1.6
Requires-Dist: MarkupSafe==3.0.2
Requires-Dist: mpmath==1.3.0
Requires-Dist: networkx==3.4.2
Requires-Dist: numpy==2.1.3
Requires-Dist: scipy==1.15.2
Requires-Dist: sympy==1.13.1
Requires-Dist: torch==2.6.0
Requires-Dist: typing_extensions==4.13.0
Dynamic: license-file
